{
  "headers": {
    "cf-cache-status": "DYNAMIC",
    "x-cache": "HIT, HIT",
    "x-fastly-request-id": "d77ca069faf3781022ee26e012ceafadc2269a99",
    "x-frame-options": "deny",
    "x-xss-protection": "1; mode=block",
    "cf-request-id": "02e73d51f90000a8d90605b200000001",
    "expires": "Sun, 24 May 2020 07:49:50 GMT",
    "x-github-request-id": "181A:0293:F58E2:13D1CA:5ECA03D5",
    "etag": "W/\"bdaae7f05b22551a182a8f16b51084c2216c6a5c788034876dda9c752b448ad0\"",
    "x-cache-hits": "1, 1",
    "x-served-by": "cache-cdg20762-CDG",
    "server": "cloudflare",
    "cf-ray": "598564c98e43a8d9-CDG",
    "x-content-type-options": "nosniff",
    "source-age": "0",
    "set-cookie": "__cfduid=d06981c23ee1da3d01dd4bd4031510e221590306290; expires=Tue, 23-Jun-20 07:44:50 GMT; path=/; domain=.deno.land; HttpOnly; SameSite=Lax; Secure",
    "vary": "Authorization,Accept-Encoding",
    "cache-control": "max-age=300",
    "access-control-allow-origin": "*",
    "x-timer": "S1590306290.183145,VS0,VE186",
    "content-security-policy": "default-src 'none'; style-src 'unsafe-inline'; sandbox",
    "expect-ct": "max-age=604800, report-uri=\"https://report-uri.cloudflare.com/cdn-cgi/beacon/expect-ct\"",
    "date": "Sun, 24 May 2020 07:44:50 GMT",
    "content-type": "application/typescript; charset=utf-8",
    "strict-transport-security": "max-age=31536000",
    "via": "1.1 varnish (Varnish/6.0), 1.1 varnish"
  },
  "url": "https://deno.land/std@0.53.0/async/mod.ts"
}